{
  "meta": {
    "title": "Wskaźnik realnego wzrostu przeciętnego wynagrodzenia (indeks)",
    "units": "percent index; 100 = poprzedni rok",
    "years": [
      "2022",
      "2023",
      "2024",
      "2025",
      "2026",
      "2027",
      "2028",
      "2029",
      "2030",
      "2031",
      "2032",
      "2035",
      "2040",
      "2045",
      "2050",
      "2055",
      "2060",
      "2065",
      "2070",
      "2075",
      "2080"
    ],
    "source": "ZUS (2022), Prognoza wpływów i wydatków Funduszu Emerytalnego do 2080 r., Tabele 1.1–1.3",
    "notes": "Wartości dla lat: 2022, 2023, 2024, 2025, 2026, 2027, 2028, 2029, 2030, 2031, 2032, 2035, 2040, 2045, 2050, 2055, 2060, 2065, 2070, 2075, 2080."
  },
  "series": {
    "variant_1": {
      "label": "Wariant nr 1 – pośredni",
      "data": {
        "2022": 98.0,
        "2023": 100.3,
        "2024": 103.4,
        "2025": 103.7,
        "2026": 103.5,
        "2027": 103.0,
        "2028": 102.9,
        "2029": 102.9,
        "2030": 102.9,
        "2031": 102.9,
        "2032": 102.9,
        "2035": 102.8,
        "2040": 102.7,
        "2045": 102.6,
        "2050": 102.5,
        "2055": 102.4,
        "2060": 102.4,
        "2065": 102.3,
        "2070": 102.2,
        "2075": 102.1,
        "2080": 102.0
      }
    },
    "variant_2": {
      "label": "Wariant nr 2 – pesymistyczny",
      "data": {
        "2022": 97.5,
        "2023": 99.8,
        "2024": 102.9,
        "2025": 103.0,
        "2026": 102.8,
        "2027": 102.5,
        "2028": 102.4,
        "2029": 102.4,
        "2030": 102.4,
        "2031": 102.4,
        "2032": 102.4,
        "2035": 102.3,
        "2040": 102.2,
        "2045": 102.1,
        "2050": 101.9,
        "2055": 101.8,
        "2060": 101.7,
        "2065": 101.6,
        "2070": 101.5,
        "2075": 101.4,
        "2080": 101.2
      }
    },
    "variant_3": {
      "label": "Wariant nr 3 – optymistyczny",
      "data": {
        "2022": 98.5,
        "2023": 100.8,
        "2024": 103.7,
        "2025": 104.0,
        "2026": 103.8,
        "2027": 103.4,
        "2028": 103.4,
        "2029": 103.4,
        "2030": 103.4,
        "2031": 103.4,
        "2032": 103.3,
        "2035": 103.3,
        "2040": 103.2,
        "2045": 103.2,
        "2050": 103.1,
        "2055": 103.1,
        "2060": 103.0,
        "2065": 102.9,
        "2070": 102.9,
        "2075": 102.8,
        "2080": 102.8
      }
    }
  }
}